tk_builder/__about__.py
tk_builder/__init__.py
tk_builder/base_elements.py
tk_builder/file_filters.py
tk_builder/image_reader.py
tk_builder/logger.py
tk_builder/panel_builder.py
tk_builder/panels/__init__.py
tk_builder/panels/image_panel.py
tk_builder/panels/pyplot_image_panel.py
tk_builder/utils/__init__.py
tk_builder/utils/color_utils.py
tk_builder/utils/frame_sequence_utils.py
tk_builder/widgets/__init__.py
tk_builder/widgets/basic_widgets.py
tk_builder/widgets/derived_widgets.py
tk_builder/widgets/image_canvas.py
tk_builder/widgets/image_canvas_tool.py
tk_builder/widgets/widget_descriptors.py
tk_builder/widgets/widget_events.py
tk_builder-1.1.8.dist-info/LICENSE
tk_builder-1.1.8.dist-info/METADATA
tk_builder-1.1.8.dist-info/WHEEL
tk_builder-1.1.8.dist-info/top_level.txt
tk_builder-1.1.8.dist-info/zip-safe
tk_builder-1.1.8.dist-info/RECORD
