Metadata-Version: 2.1
Name: tk-builder
Version: 1.1.8
Summary: This provides a set tools for simple creation of graphical user interfaces for Python based on the tkinter library. The main focus for the GUIs is assumed to be on overhead imaging applications.
Home-page: https://github.com/ngageoint/tk_builder
Author: National Geospatial-Intelligence Agency
Author-email: Wade.C.Schwartzkopf@nga.mil
License: MIT
Platform: any
Classifier: Development Status :: 4 - Beta
Classifier: Intended Audience :: Developers
Classifier: License :: OSI Approved :: MIT License
Classifier: Programming Language :: Python :: 3
Classifier: Programming Language :: Python :: 3.6
Classifier: Programming Language :: Python :: 3.7
Classifier: Programming Language :: Python :: 3.8
Classifier: Programming Language :: Python :: 3.9
License-File: LICENSE
Requires-Dist: numpy
Requires-Dist: scipy
Requires-Dist: matplotlib
Requires-Dist: Pillow
Requires-Dist: sarpy (>=1.2.36)
